LICENSE.txt
README.md
pyproject.toml
setup.cfg
setup.py
src/pydmart/__init__.py
src/pydmart/py.typed
src/pydmart/service.py
src/pydmart2.egg-info/PKG-INFO
src/pydmart2.egg-info/SOURCES.txt
src/pydmart2.egg-info/dependency_links.txt
src/pydmart2.egg-info/top_level.txt