Metadata-Version: 2.1
Name: pydmart2
Version: 0.0.9
Summary: A client to connect to a Dmart isntance
Home-page: https://github.com/edraj/pydmart
Author: <Kefah Issa>
Author-email: kefah.issa@gmail.com
Classifier: Programming Language :: Python :: 3
Classifier: License :: OSI Approved :: MIT License
Classifier: Operating System :: OS Independent
License-File: LICENSE.txt
